monkeybrain/__init__.py
monkeybrain-0.2.3.dist-info/METADATA
monkeybrain-0.2.3.dist-info/WHEEL
monkeybrain-0.2.3.dist-info/entry_points.txt
monkeybrain-0.2.3.dist-info/top_level.txt
monkeybrain-0.2.3.dist-info/RECORD
