Metadata-Version: 2.4
Name: monkeybrain
Version: 0.2.3
Summary: A CLI-Tool for launching TouchDesigner projects.
Author-email: Wieland Hilker <Wieland@PlusPlus.One>
License-Expression: MIT
Project-URL: Website, https://plusplus.one
Project-URL: Repository, https://github.com/PlusPlusOneGmbH/Monkeybrain
Keywords: TouchDesigner,UV,WindowsOnly
Requires-Python: >=3.11
Requires-Dist: python-dotenv>=1.1.1
